rlcropwater/__init__.py
rlcropwater/common.py
rlcropwater/rlcropwater.py
rlcropwater-0.0.1.dist-info/LICENSE
rlcropwater-0.0.1.dist-info/METADATA
rlcropwater-0.0.1.dist-info/WHEEL
rlcropwater-0.0.1.dist-info/entry_points.txt
rlcropwater-0.0.1.dist-info/top_level.txt
rlcropwater-0.0.1.dist-info/RECORD
